cellori/__init__.py
cellori/cellori.py
cellori/imshowfast.py
cellori/netmap.py
cellori/run_gui.py
cellori/utils.py
cellori-3.7.dist-info/LICENSE
cellori-3.7.dist-info/METADATA
cellori-3.7.dist-info/WHEEL
cellori-3.7.dist-info/top_level.txt
cellori-3.7.dist-info/RECORD
