Metadata-Version: 2.1
Name: cellori
Version: 3.7
Summary: Cellori
Home-page: UNKNOWN
Author: William Niu
Author-email: <wniu721@gmail.com>
License: UNKNOWN
Keywords: nuclei,segmentation
Platform: UNKNOWN
Classifier: Development Status :: 5 - Production/Stable
Classifier: Intended Audience :: Science/Research
Classifier: Programming Language :: Python :: 3
Classifier: Operating System :: Unix
Classifier: Operating System :: MacOS :: MacOS X
Classifier: Operating System :: Microsoft :: Windows
License-File: LICENSE
Requires-Dist: dask
Requires-Dist: numba
Requires-Dist: numpy
Requires-Dist: opencv-python
Requires-Dist: scikit-image
Requires-Dist: scipy
Requires-Dist: simpleitk
Requires-Dist: stitchwell
Requires-Dist: tifffile
Provides-Extra: gui
Requires-Dist: matplotlib ; extra == 'gui'
Requires-Dist: pyside6 ; extra == 'gui'
